spotdl_rockbox/__init__.py
spotdl_rockbox/__main__.py
spotdl_rockbox/_version.py
spotdl_rockbox/console/__init__.py
spotdl_rockbox/console/download.py
spotdl_rockbox/console/entry_point.py
spotdl_rockbox/console/meta.py
spotdl_rockbox/console/save.py
spotdl_rockbox/console/sync.py
spotdl_rockbox/console/url.py
spotdl_rockbox/console/web.py
spotdl_rockbox/download/__init__.py
spotdl_rockbox/download/downloader.py
spotdl_rockbox/download/progress_handler.py
spotdl_rockbox/providers/__init__.py
spotdl_rockbox/providers/audio/__init__.py
spotdl_rockbox/providers/audio/bandcamp.py
spotdl_rockbox/providers/audio/base.py
spotdl_rockbox/providers/audio/piped.py
spotdl_rockbox/providers/audio/sliderkz.py
spotdl_rockbox/providers/audio/soundcloud.py
spotdl_rockbox/providers/audio/youtube.py
spotdl_rockbox/providers/audio/ytmusic.py
spotdl_rockbox/providers/lyrics/__init__.py
spotdl_rockbox/providers/lyrics/azlyrics.py
spotdl_rockbox/providers/lyrics/base.py
spotdl_rockbox/providers/lyrics/genius.py
spotdl_rockbox/providers/lyrics/musixmatch.py
spotdl_rockbox/providers/lyrics/synced.py
spotdl_rockbox/types/__init__.py
spotdl_rockbox/types/album.py
spotdl_rockbox/types/artist.py
spotdl_rockbox/types/options.py
spotdl_rockbox/types/playlist.py
spotdl_rockbox/types/result.py
spotdl_rockbox/types/saved.py
spotdl_rockbox/types/song.py
spotdl_rockbox/utils/__init__.py
spotdl_rockbox/utils/archive.py
spotdl_rockbox/utils/arguments.py
spotdl_rockbox/utils/config.py
spotdl_rockbox/utils/console.py
spotdl_rockbox/utils/downloader.py
spotdl_rockbox/utils/ffmpeg.py
spotdl_rockbox/utils/formatter.py
spotdl_rockbox/utils/logging.py
spotdl_rockbox/utils/lrc.py
spotdl_rockbox/utils/m3u.py
spotdl_rockbox/utils/matching.py
spotdl_rockbox/utils/metadata.py
spotdl_rockbox/utils/search.py
spotdl_rockbox/utils/spotify.py
spotdl_rockbox/utils/static.py
spotdl_rockbox/utils/web.py
spotdl_rockbox-4.2.7.1.dist-info/entry_points.txt
spotdl_rockbox-4.2.7.1.dist-info/LICENSE
spotdl_rockbox-4.2.7.1.dist-info/METADATA
spotdl_rockbox-4.2.7.1.dist-info/WHEEL
spotdl_rockbox-4.2.7.1.dist-info/RECORD
