Metadata-Version: 2.1
Name: spotdl_rockbox
Version: 4.2.7.1
Summary: Fox for rockbox. Download your Spotify playlists and songs along with album art and metadata
Home-page: https://github.com/spotDL/spotify-downloader/
License: MIT
Keywords: spotify,downloader,spotdl,music
Author: spotDL Team
Author-email: spotdladmins@googlegroups.com
Maintainer: xnetcat
Maintainer-email: xnetcat.dev@gmail.com
Requires-Python: >=3.8,<3.13
Classifier: Intended Audience :: End Users/Desktop
Classifier: License :: OSI Approved :: MIT License
Classifier: Programming Language :: Python
Classifier: Programming Language :: Python :: 3
Classifier: Programming Language :: Python :: 3.8
Classifier: Programming Language :: Python :: 3.9
Classifier: Programming Language :: Python :: 3.10
Classifier: Programming Language :: Python :: 3.11
Classifier: Programming Language :: Python :: 3.12
Classifier: Programming Language :: Python :: 3 :: Only
Classifier: Topic :: Multimedia
Classifier: Topic :: Multimedia :: Sound/Audio
Classifier: Topic :: Utilities
Requires-Dist: beautifulsoup4 (>=4.12.3,<5.0.0)
Requires-Dist: fastapi (>=0.103.0,<0.104.0)
Requires-Dist: mutagen (>=1.47.0,<2.0.0)
Requires-Dist: platformdirs (>=4.2.0,<5.0.0)
Requires-Dist: pydantic (>=2.6.4,<3.0.0)
Requires-Dist: pykakasi (>=2.2.1,<3.0.0)
Requires-Dist: python-slugify[unidecode] (>=8.0.4,<9.0.0)
Requires-Dist: pytube (>=15.0.0,<16.0.0)
Requires-Dist: rapidfuzz (>=3.7.0,<4.0.0)
Requires-Dist: requests (>=2.31.0,<3.0.0)
Requires-Dist: rich (>=13.7.1,<14.0.0)
Requires-Dist: setuptools (>=69.2.0,<70.0.0)
Requires-Dist: soundcloud-v2 (>=1.3.7,<2.0.0)
Requires-Dist: spotipy (>=2.23.0,<3.0.0)
Requires-Dist: syncedlyrics (>=0.7.0,<0.8.0)
Requires-Dist: uvicorn (>=0.23.2,<0.24.0)
Requires-Dist: yt-dlp (>=2024.3.10,<2025.0.0)
Requires-Dist: ytmusicapi (>=1.3.2,<2.0.0) ; python_version < "3.10"
Requires-Dist: ytmusicapi (>=1.4.1,<2.0.0) ; python_version >= "3.10"
Project-URL: Documentation, https://spotdl.rtfd.io/en/latest/
Project-URL: Repository, https://github.com/MisteryDush/spotify-downloader-rockbox.git
